pyticket_analytics/__init__.py
pyticket_analytics/pyticket_analytics.py
pyticket_analytics/pyticket_query.py
pyticket_analytics-0.1.0.dist-info/LICENSE
pyticket_analytics-0.1.0.dist-info/WHEEL
pyticket_analytics-0.1.0.dist-info/METADATA
pyticket_analytics-0.1.0.dist-info/RECORD
