Metadata-Version: 2.1
Name: pyticket-analytics
Version: 0.1.0
Summary: A python package to access ticketmaster data using python, and to provide tools for simple data analytics for the accessed data.
License: MIT
Author: Ega Kurnia Yazid
Requires-Python: >=3.9,<4.0
Classifier: License :: OSI Approved :: MIT License
Classifier: Programming Language :: Python :: 3
Classifier: Programming Language :: Python :: 3.9
Classifier: Programming Language :: Python :: 3.10
Classifier: Programming Language :: Python :: 3.11
Requires-Dist: dotenv (>=0.0.5,<0.0.6)
Requires-Dist: numpy (>=1.23.5,<2.0.0)
Requires-Dist: pandas (>=1.5.2,<2.0.0)
Requires-Dist: python-dotenv (>=0.21.0,<0.22.0)
Requires-Dist: requests (>=2.28.1,<3.0.0)
